vmguestlib.py
vmguestlib_mod-0.1.5.data/scripts/vmguest-stats
vmguestlib_mod-0.1.5.dist-info/AUTHORS
vmguestlib_mod-0.1.5.dist-info/LICENSE
vmguestlib_mod-0.1.5.dist-info/METADATA
vmguestlib_mod-0.1.5.dist-info/WHEEL
vmguestlib_mod-0.1.5.dist-info/top_level.txt
vmguestlib_mod-0.1.5.dist-info/RECORD
